[{
  "_id": {
    "$oid": "682cc5c9e6e82b18cb501bda"
  },
  "label": "ไฟไม่ติด",
  "iconUrl": "https://storage.googleapis.com/glide-prod.appspot.com/uploads-v2/xopRrFxPyckUrVLm522j/pub/1kZl0wgoQTE7LAmJeRPk.png",
  "category": "ไฟส่องสว่าง",
  "active": true,
  "__v": 0
},
{
  "_id": {
    "$oid": "682cc75ee6e82b18cb501bdc"
  },
  "label": "ติดๆดับๆ",
  "iconUrl": "https://storage.googleapis.com/glide-prod.appspot.com/uploads-v2/xopRrFxPyckUrVLm522j/pub/d66EwCvRBgaim80t5W6x.png",
  "category": "ไฟส่องสว่าง",
  "active": true,
  "__v": 0
},
{
  "_id": {
    "$oid": "682cc7bfe6e82b18cb501bde"
  },
  "label": "สายไฟชำรุด",
  "iconUrl": "https://storage.googleapis.com/glide-prod.appspot.com/uploads-v2/xopRrFxPyckUrVLm522j/pub/kRn1TKax7mLQeofcNKW1.png",
  "category": "ไฟส่องสว่าง",
  "active": true,
  "__v": 0
},
{
  "_id": {
    "$oid": "682cc7ffe6e82b18cb501be0"
  },
  "label": "ท่อแตก",
  "iconUrl": "https://storage.googleapis.com/glide-prod.appspot.com/uploads-v2/xopRrFxPyckUrVLm522j/pub/VmdLjqnPcUJg8J7yjMKA.png",
  "category": "น้ำประปา",
  "active": true,
  "__v": 0
},
{
  "_id": {
    "$oid": "682cc835e6e82b18cb501be2"
  },
  "label": "น้ำรั่วซึม",
  "iconUrl": "https://storage.googleapis.com/glide-prod.appspot.com/uploads-v2/xopRrFxPyckUrVLm522j/pub/Mx3788baubaj4VavEuqb.png",
  "category": "น้ำประปา",
  "active": true,
  "__v": 0
},
{
  "_id": {
    "$oid": "682cc875e6e82b18cb501be4"
  },
  "label": "มาตรชำรุด",
  "iconUrl": "https://storage.googleapis.com/glide-prod.appspot.com/uploads-v2/xopRrFxPyckUrVLm522j/pub/ufe9OKo4XzQ2pIFqUIbF.png",
  "category": "น้ำประปา",
  "active": true,
  "__v": 0
},
{
  "_id": {
    "$oid": "682cc8b4e6e82b18cb501be6"
  },
  "label": "ผิวจราจรเป็นหลุม",
  "iconUrl": "https://storage.googleapis.com/glide-prod.appspot.com/uploads-v2/xopRrFxPyckUrVLm522j/pub/eAeA90q5C4xTASdjcoUk.png",
  "category": "ถนน/ทางเท้า",
  "active": true,
  "__v": 0
},
{
  "_id": {
    "$oid": "682eadcae8a370e80afe5d62"
  },
  "label": "กิ่งไม้ล้ำถนน",
  "iconUrl": "https://storage.googleapis.com/glide-prod.appspot.com/uploads-v2/xopRrFxPyckUrVLm522j/pub/u8hEJbnNRzR93NME0sHW.png",
  "category": "ถนน/ทางเท้า",
  "active": true,
  "__v": 0
},
{
  "_id": {
    "$oid": "682eb513d1848b72ec96179c"
  },
  "label": "ฝาท่อชำรุด",
  "iconUrl": "https://storage.googleapis.com/glide-prod.appspot.com/uploads-v2/xopRrFxPyckUrVLm522j/pub/FLFv5pzyqN3bOwjBn40W.png",
  "category": "ถนน/ทางเท้า",
  "active": true,
  "__v": 0
},
{
  "_id": {
    "$oid": "682eb8b9d1848b72ec96179e"
  },
  "label": "ขอความอนุเคราะห์",
  "iconUrl": "https://storage.googleapis.com/glide-prod.appspot.com/uploads-v2/xopRrFxPyckUrVLm522j/pub/RvKGh8I3fklPDL49GYhz.png",
  "category": "ถนน/ทางเท้า",
  "active": true,
  "__v": 0
},
{
  "_id": {
    "$oid": "682eb923d1848b72ec9617a2"
  },
  "label": "ขอรถรับ-ส่งไปโรงพยาบาล",
  "iconUrl": "https://storage.googleapis.com/glide-prod.appspot.com/uploads-v2/xopRrFxPyckUrVLm522j/pub/1PbEQywTnZmxYy0IvYVR.png",
  "category": "สวัสดิการสังคม",
  "active": true,
  "__v": 0
},
{
  "_id": {
    "$oid": "682eb9a2d1848b72ec9617a6"
  },
  "label": "ร้องเรียนร้องทุกข์",
  "iconUrl": "https://storage.googleapis.com/glide-prod.appspot.com/uploads-v2/xopRrFxPyckUrVLm522j/pub/FVd1fg52IgMmSsmgbt0a.png",
  "category": "อื่นๆ",
  "active": true,
  "__v": 0
},
{
  "_id": {
    "$oid": "682eb9c6d1848b72ec9617a8"
  },
  "label": "ติดต่อสอบถาม",
  "iconUrl": "https://storage.googleapis.com/glide-prod.appspot.com/uploads-v2/xopRrFxPyckUrVLm522j/pub/4INv9wdlHpiV2RWUIeNC.png",
  "category": "อื่นๆ",
  "active": true,
  "__v": 0
},
{
  "_id": {
    "$oid": "682eb9f3d1848b72ec9617aa"
  },
  "label": "คัตเอาท์ชำรุด",
  "iconUrl": "https://storage.googleapis.com/glide-prod.appspot.com/uploads-v2/xopRrFxPyckUrVLm522j/pub/lf2qbithGlefgiDljOp2.png",
  "category": "ไฟส่องสว่าง",
  "active": true,
  "__v": 0
},
{
  "_id": {
    "$oid": "682eba20d1848b72ec9617ac"
  },
  "label": "แรงดันน้ำตก",
  "iconUrl": "https://storage.googleapis.com/glide-prod.appspot.com/uploads-v2/xopRrFxPyckUrVLm522j/pub/CXV4fKVsxwcItRY2njlb.png",
  "category": "น้ำประปา",
  "active": true,
  "__v": 0
},
{
  "_id": {
    "$oid": "682eba43d1848b72ec9617ae"
  },
  "label": "คุณภาพน้ำ",
  "iconUrl": "https://storage.googleapis.com/glide-prod.appspot.com/uploads-v2/xopRrFxPyckUrVLm522j/pub/cuwsc1RmzjgiaYueGaRX.png",
  "category": "น้ำประปา",
  "active": true,
  "__v": 0
},
{
  "_id": {
    "$oid": "682eba67d1848b72ec9617b0"
  },
  "label": "ถังชำรุด",
  "iconUrl": "https://storage.googleapis.com/glide-prod.appspot.com/uploads-v2/xopRrFxPyckUrVLm522j/pub/6QjIsflV5yjzabqqaOdE.png",
  "category": "ขยะมูลฝอย",
  "active": true,
  "__v": 0
},
{
  "_id": {
    "$oid": "682eba8ad1848b72ec9617b2"
  },
  "label": "กลิ่นรบกวน",
  "iconUrl": "https://storage.googleapis.com/glide-prod.appspot.com/uploads-v2/xopRrFxPyckUrVLm522j/pub/YxSYz2NJY4DL0uESV0Lp.png",
  "category": "ขยะมูลฝอย",
  "active": true,
  "__v": 0
},
{
  "_id": {
    "$oid": "682ebaaed1848b72ec9617b4"
  },
  "label": "ถังไม่เพียงพอ",
  "iconUrl": "https://storage.googleapis.com/glide-prod.appspot.com/uploads-v2/xopRrFxPyckUrVLm522j/pub/Ae0sGJnNfztovSZYnREL.png",
  "category": "ขยะมูลฝอย",
  "active": true,
  "__v": 0
},
{
  "_id": {
    "$oid": "682ebacbd1848b72ec9617b6"
  },
  "label": "ขยะล้นถัง",
  "iconUrl": "https://storage.googleapis.com/glide-prod.appspot.com/uploads-v2/xopRrFxPyckUrVLm522j/pub/dmXcDZeWLXU4VcE1af9F.png",
  "category": "ขยะมูลฝอย",
  "active": true,
  "__v": 0
},
{
  "_id": {
    "$oid": "682ebb28d1848b72ec9617ba"
  },
  "label": "ปัญหาครอบครัว/ความรุนแรง",
  "iconUrl": "https://cdn-icons-png.flaticon.com/128/6024/6024161.png",
  "category": "สวัสดิการสังคม",
  "active": true,
  "__v": 0
},
{
  "_id": {
    "$oid": "683083120e3b4a9577b70c15"
  },
  "label": "คำร้องช่วยเหลือทั่วไป",
  "iconUrl": "https://cdn-icons-png.flaticon.com/128/2936/2936905.png",
  "category": "สวัสดิการสังคม",
  "active": true,
  "__v": 0
},
{
  "_id": {
    "$oid": "6830c310f8b9a32bdeb410a3"
  },
  "label": "ความสะอาด",
  "iconUrl": "https://storage.googleapis.com/glide-prod.appspot.com/uploads-v2/xopRrFxPyckUrVLm522j/pub/B6VHDfXT1VUTZYUyE6iv.png",
  "category": "ถนน/ทางเท้า",
  "active": true,
  "__v": 0
},
{
  "_id": {
    "$oid": "6831b4a80f2bfeec5598194b"
  },
  "label": "แจ้งเหตุด่วน",
  "iconUrl": "https://res.cloudinary.com/dczmhfvgh/image/upload/v1748087967/lz04vwckb3ih4q2zv86y.png",
  "category": "อื่นๆ",
  "active": true,
  "__v": 0
},
{
  "_id": {
    "$oid": "683927680b754d852aca140c"
  },
  "label": "ผู้สูงอายุขอความช่วยเหลือ",
  "iconUrl": "https://cdn-icons-png.flaticon.com/128/3090/3090757.png",
  "category": "สวัสดิการสังคม",
  "active": true,
  "__v": 0
},
{
  "_id": {
    "$oid": "683927a20b754d852aca1410"
  },
  "label": "ขอยืมกายอุปกรณ์",
  "iconUrl": "https://storage.googleapis.com/glide-prod.appspot.com/uploads-v2/xopRrFxPyckUrVLm522j/pub/0bbvQeNCcDl6hgsOsB3j.png",
  "category": "สวัสดิการสังคม",
  "active": true,
  "__v": 0
},
{
  "_id": {
    "$oid": "683927fd0b754d852aca1416"
  },
  "label": "ต้องการติดตั้งชุดหลอดไฟ",
  "iconUrl": "https://cdn-icons-png.flaticon.com/128/6369/6369160.png",
  "category": "ไฟส่องสว่าง",
  "active": true,
  "__v": 0
},
{
  "_id": {
    "$oid": "683928280b754d852aca1418"
  },
  "label": "ไฟหันผิดทิศทาง",
  "iconUrl": "https://cdn-icons-png.flaticon.com/128/7402/7402216.png",
  "category": "ไฟส่องสว่าง",
  "active": true,
  "__v": 0
},
{
  "_id": {
    "$oid": "6839283f0b754d852aca141a"
  },
  "label": "แสงสว่างไม่เพียงพอ",
  "iconUrl": "https://cdn-icons-png.flaticon.com/128/1299/1299025.png",
  "category": "ไฟส่องสว่าง",
  "active": true,
  "__v": 0
},
{
  "_id": {
    "$oid": "683928640b754d852aca141c"
  },
  "label": "ฝาท่อชำรุด/สูญหาย",
  "iconUrl": "https://storage.googleapis.com/glide-prod.appspot.com/uploads-v2/xopRrFxPyckUrVLm522j/pub/FLFv5pzyqN3bOwjBn40W.png",
  "category": "ถนน/ทางเท้า",
  "active": true,
  "__v": 0
},
{
  "_id": {
    "$oid": "683928dd0b754d852aca1428"
  },
  "label": "ขอรับวัคซีนป้องกันโรคพิษสุนัขบ้า",
  "iconUrl": "https://cdn-icons-png.flaticon.com/128/8718/8718993.png",
  "category": "สัตว์เลี้ยง",
  "active": true,
  "__v": 0
},
{
  "_id": {
    "$oid": "6839290b0b754d852aca142a"
  },
  "label": "แจ้งเสียงไร้สาย ระดับเสียงเบาหรือดังเกินไป",
  "iconUrl": "https://cdn-icons-png.flaticon.com/128/1592/1592478.png",
  "category": "เสียงไร้สาย",
  "active": true,
  "__v": 0
},
{
  "_id": {
    "$oid": "683929510b754d852aca1435"
  },
  "label": "ฝากข่าวประชาสัมพันธ์",
  "iconUrl": "https://cdn-icons-png.flaticon.com/128/2327/2327169.png",
  "category": "เสียงไร้สาย",
  "active": true,
  "__v": 0
},
{
  "_id": {
    "$oid": "6839296b0b754d852aca1437"
  },
  "label": "รางระบายน้ำอุดตัน",
  "iconUrl": "https://cdn-icons-png.flaticon.com/128/8836/8836915.png",
  "category": "ถนน/ทางเท้า",
  "active": true,
  "__v": 0
},
{
  "_id": {
    "$oid": "683929750b754d852aca1439"
  },
  "label": "อื่นๆ(โปรดระบุ)",
  "iconUrl": "https://cdn-icons-png.flaticon.com/128/3688/3688597.png",
  "category": "ถนน/ทางเท้า",
  "active": true,
  "__v": 0
},
{
  "_id": {
    "$oid": "6839c076033cb37fbde17d34"
  },
  "label": "เสียงสัตว์รบกวน",
  "iconUrl": "https://cdn-icons-png.flaticon.com/128/176/176529.png",
  "category": "สัตว์เลี้ยง",
  "active": true,
  "__v": 0
},
{
  "_id": {
    "$oid": "6846fd8907e9516ba96300b0"
  },
  "label": "กลิ่นรบกวน",
  "iconUrl": "https://cdn-icons-png.flaticon.com/128/2829/2829804.png",
  "category": "สัตว์เลี้ยง",
  "active": true,
  "__v": 0
},
{
  "_id": {
    "$oid": "6847126507e9516ba96300d7"
  },
  "label": "ติดต่อหน่วยงาน",
  "iconUrl": "https://cdn-icons-png.flaticon.com/128/7412/7412542.png",
  "category": "อื่นๆ",
  "active": true,
  "__v": 0
}]